pygeppetto/__init__.py
pygeppetto/constants.py
pygeppetto/data_model.py
pygeppetto/geppetto_manager.py
pygeppetto/local_data_model.py
pygeppetto/ui.py
pygeppetto/utils.py
pygeppetto/api/__init__.py
pygeppetto/api/inbound_messages.py
pygeppetto/api/message_handler.py
pygeppetto/api/messaging.py
pygeppetto/api/outbound_messages.py
pygeppetto/ecore/GeppettoCommonLibrary.xmi
pygeppetto/ecore/geppettoModel.ecore
pygeppetto/managers/__init__.py
pygeppetto/managers/experiment_manager.py
pygeppetto/managers/experiment_run_manager.py
pygeppetto/managers/geppetto_manager.py
pygeppetto/managers/project_manager.py
pygeppetto/managers/runtime_experiment.py
pygeppetto/managers/runtime_project.py
pygeppetto/managers/runtime_tree_manager.py
pygeppetto/model/__init__.py
pygeppetto/model/exceptions.py
pygeppetto/model/geppetto_resource.py
pygeppetto/model/model.py
pygeppetto/model/model_access.py
pygeppetto/model/model_factory.py
pygeppetto/model/model_serializer.py
pygeppetto/model/model_utility.py
pygeppetto/model/overrides.py
pygeppetto/model/utils.py
pygeppetto/model/datasources/__init__.py
pygeppetto/model/datasources/datasources.py
pygeppetto/model/instances/__init__.py
pygeppetto/model/instances/instances.py
pygeppetto/model/types/__init__.py
pygeppetto/model/types/types.py
pygeppetto/model/utils/__init__.py
pygeppetto/model/utils/bytesuri.py
pygeppetto/model/utils/datasource.py
pygeppetto/model/utils/model_traversal.py
pygeppetto/model/utils/pointer_utility.py
pygeppetto/model/utils/template.py
pygeppetto/model/utils/url_reader.py
pygeppetto/model/values/__init__.py
pygeppetto/model/values/values.py
pygeppetto/model/variables/__init__.py
pygeppetto/model/variables/variables.py
pygeppetto/services/__init__.py
pygeppetto/services/data_manager.py
pygeppetto/services/data_source_service.py
pygeppetto/services/model_interpreter.py
pygeppetto/services/data_source/__init__.py
pygeppetto/services/data_source/neo4j.py
pygeppetto/visitors/__init__.py
pygeppetto-0.9.1.dist-info/LICENSE
pygeppetto-0.9.1.dist-info/METADATA
pygeppetto-0.9.1.dist-info/WHEEL
pygeppetto-0.9.1.dist-info/top_level.txt
pygeppetto-0.9.1.dist-info/RECORD
