Metadata-Version: 2.1
Name: pygeppetto
Version: 0.9.1
Summary: Geppetto Python API for creating a Geppetto Model from Python
Home-page: https://github.com/openworm/pygeppetto
Author: The Geppetto Development Team
Author-email: info@geppetto.org
License: MIT
Keywords: geppetto openworm Python
Classifier: Programming Language :: Python
Classifier: Programming Language :: Python :: 3
Classifier: Programming Language :: Python :: 3.10
Classifier: Programming Language :: Python :: 3.11
Classifier: Programming Language :: Python :: 3.12
Classifier: Programming Language :: Python :: 3.13
Classifier: Operating System :: OS Independent
Classifier: Intended Audience :: Developers
Classifier: Topic :: Software Development
Classifier: Topic :: Software Development :: Libraries
License-File: LICENSE
Requires-Dist: pyecore>=0.11.5
Requires-Dist: multimethod
Requires-Dist: deprecated
Requires-Dist: airspeed
Requires-Dist: requests>=2.0.0
Provides-Extra: testing
Requires-Dist: pytest; extra == "testing"
Requires-Dist: responses; extra == "testing"
